{
	"credit": "Made with Blockbench",
	"textures": {
		"inner": "-inner",
		"bottom": "-bottom",
		"top": "-top",
		"particle": "-side",
		"side": "-side"
	},
	"elements": [
		{
			"from": [1, 0, 1],
			"to": [15, 8, 15],
			"faces": {
				"north": {"uv": [1, 8, 15, 16], "texture": "#side"},
				"east": {"uv": [1, 8, 15, 16], "texture": "#side"},
				"south": {"uv": [1, 8, 15, 16], "texture": "#side"},
				"west": {"uv": [1, 8, 15, 16], "texture": "#side"},
				"up": {"uv": [1, 1, 15, 15], "texture": "#top"},
				"down": {"uv": [1, 1, 15, 15], "texture": "#bottom", "cullface": "down"}
			}
		},
		{
			"from": [11, 8, 2],
			"to": [14, 16, 14],
			"rotation": {"angle": 0, "axis": "y", "origin": [8, 16, 8]},
			"faces": {
				"north": {"uv": [2, 8, 5, 16], "texture": "#side_up"},
				"east": {"uv": [2, 8, 14, 16], "texture": "#side_up"},
				"south": {"uv": [11, 8, 14, 16], "texture": "#side_up"},
				"west": {"uv": [2, 8, 14, 16], "texture": "#inner"},
				"up": {"uv": [11, 2, 14, 14], "texture": "#top_up", "cullface": "up"}
			}
		}
	]
}